LICENSE
MANIFEST.in
README.md
setup.py
plexcli/__init__.py
plexcli/api.py
plexcli/main.py
plexcli/shell.py
plexcli/util.py
plexcli.egg-info/PKG-INFO
plexcli.egg-info/SOURCES.txt
plexcli.egg-info/dependency_links.txt
plexcli.egg-info/entry_points.txt
plexcli.egg-info/requires.txt
plexcli.egg-info/top_level.txt
plexcli/commands/__init__.py
plexcli/commands/activity.py
plexcli/commands/base.py
plexcli/commands/clients.py
plexcli/commands/media.py
plexcli/commands/servers.py
plexcli/commands/sessions.py