Metadata-Version: 1.1
Name: plexcli
Version: 0.3.0
Summary: Command Line Interface for Plex
Home-page: https://github.com/mayfield/plexcli/
Author: Justin Mayfield
Author-email: tooker@gmail.com
License: MIT
Platform: UNKNOWN
Classifier: Development Status :: 3 - Alpha
Classifier: Intended Audience :: Developers
Classifier: License :: OSI Approved :: MIT License
Classifier: Operating System :: OS Independent
Classifier: Programming Language :: Python
Classifier: Programming Language :: Python :: 3.4
Classifier: Programming Language :: Python :: 3.5
